{"id":"feiertage--ms","group":"Feiertage","label":"Montserrat","url":"/feiertage/ms/","feedUrl":"/feeds/feiertage/ms.ics","windows":[{"from":"2026-01-01","to":"2026-01-01","description":"New Year's Day"},{"from":"2026-03-17","to":"2026-03-17","description":"Saint Patrick's Day"},{"from":"2026-04-03","to":"2026-04-03","description":"Good Friday"},{"from":"2026-04-06","to":"2026-04-06","description":"Easter Monday"},{"from":"2026-05-04","to":"2026-05-04","description":"Labour Day"},{"from":"2026-05-25","to":"2026-05-25","description":"Whit Monday"},{"from":"2026-06-15","to":"2026-06-15","description":"Queen's Birthday Celebration"},{"from":"2026-08-03","to":"2026-08-03","description":"Emancipation Day"},{"from":"2026-12-25","to":"2026-12-25","description":"Christmas Day"},{"from":"2026-12-26","to":"2026-12-26","description":"Boxing Day"},{"from":"2026-12-28","to":"2026-12-28","description":"Boxing Day (substitute day)"},{"from":"2026-12-31","to":"2026-12-31","description":"Festival Day"},{"from":"2027-01-01","to":"2027-01-01","description":"New Year's Day"},{"from":"2027-03-17","to":"2027-03-17","description":"Saint Patrick's Day"},{"from":"2027-03-26","to":"2027-03-26","description":"Good Friday"},{"from":"2027-03-29","to":"2027-03-29","description":"Easter Monday"},{"from":"2027-05-03","to":"2027-05-03","description":"Labour Day"},{"from":"2027-05-17","to":"2027-05-17","description":"Whit Monday"},{"from":"2027-06-14","to":"2027-06-14","description":"Queen's Birthday Celebration"},{"from":"2027-08-02","to":"2027-08-02","description":"Emancipation Day"},{"from":"2027-12-25","to":"2027-12-25","description":"Christmas Day"},{"from":"2027-12-26","to":"2027-12-26","description":"Boxing Day"},{"from":"2027-12-27","to":"2027-12-27","description":"Christmas Day (substitute day)"},{"from":"2027-12-28","to":"2027-12-28","description":"Boxing Day (substitute day)"},{"from":"2027-12-31","to":"2027-12-31","description":"Festival Day"},{"from":"2028-01-01","to":"2028-01-01","description":"New Year's Day"},{"from":"2028-01-03","to":"2028-01-03","description":"New Year's Day (substitute day)"},{"from":"2028-03-17","to":"2028-03-17","description":"Saint Patrick's Day"},{"from":"2028-04-14","to":"2028-04-14","description":"Good Friday"},{"from":"2028-04-17","to":"2028-04-17","description":"Easter Monday"},{"from":"2028-05-01","to":"2028-05-01","description":"Labour Day"},{"from":"2028-06-05","to":"2028-06-05","description":"Whit Monday"},{"from":"2028-06-12","to":"2028-06-12","description":"Queen's Birthday Celebration"},{"from":"2028-08-01","to":"2028-08-01","description":"Emancipation Day"},{"from":"2028-12-25","to":"2028-12-25","description":"Christmas Day"},{"from":"2028-12-26","to":"2028-12-26","description":"Boxing Day"},{"from":"2028-12-31","to":"2028-12-31","description":"Festival Day"}]}