{"id":"feiertage--sk","group":"Feiertage","label":"Slovenská republika","url":"/feiertage/sk/","feedUrl":"/feeds/feiertage/sk.ics","windows":[{"from":"2026-01-01","to":"2026-01-01","description":"Deň vzniku Slovenskej republiky"},{"from":"2026-01-06","to":"2026-01-06","description":"Zjavenie Pána"},{"from":"2026-04-03","to":"2026-04-03","description":"Veľkonočný piatok"},{"from":"2026-04-05","to":"2026-04-05","description":"Veľká noc"},{"from":"2026-04-06","to":"2026-04-06","description":"Veľkonočný pondelok"},{"from":"2026-05-01","to":"2026-05-01","description":"Sviatok práce"},{"from":"2026-07-05","to":"2026-07-05","description":"Sviatok svätého Cyrila a Metoda"},{"from":"2026-08-29","to":"2026-08-29","description":"Výročie Slovenského národného povstania"},{"from":"2026-11-01","to":"2026-11-01","description":"Sviatok všetkých svätých"},{"from":"2026-12-24","to":"2026-12-24","description":"Štedrý deň"},{"from":"2026-12-25","to":"2026-12-25","description":"Prvý sviatok vianočný"},{"from":"2026-12-26","to":"2026-12-26","description":"Druhý sviatok vianočný"},{"from":"2027-01-01","to":"2027-01-01","description":"Deň vzniku Slovenskej republiky"},{"from":"2027-01-06","to":"2027-01-06","description":"Zjavenie Pána"},{"from":"2027-03-26","to":"2027-03-26","description":"Veľkonočný piatok"},{"from":"2027-03-28","to":"2027-03-28","description":"Veľká noc"},{"from":"2027-03-29","to":"2027-03-29","description":"Veľkonočný pondelok"},{"from":"2027-05-01","to":"2027-05-01","description":"Sviatok práce"},{"from":"2027-07-05","to":"2027-07-05","description":"Sviatok svätého Cyrila a Metoda"},{"from":"2027-08-29","to":"2027-08-29","description":"Výročie Slovenského národného povstania"},{"from":"2027-11-01","to":"2027-11-01","description":"Sviatok všetkých svätých"},{"from":"2027-12-24","to":"2027-12-24","description":"Štedrý deň"},{"from":"2027-12-25","to":"2027-12-25","description":"Prvý sviatok vianočný"},{"from":"2027-12-26","to":"2027-12-26","description":"Druhý sviatok vianočný"},{"from":"2028-01-01","to":"2028-01-01","description":"Deň vzniku Slovenskej republiky"},{"from":"2028-01-06","to":"2028-01-06","description":"Zjavenie Pána"},{"from":"2028-04-14","to":"2028-04-14","description":"Veľkonočný piatok"},{"from":"2028-04-16","to":"2028-04-16","description":"Veľká noc"},{"from":"2028-04-17","to":"2028-04-17","description":"Veľkonočný pondelok"},{"from":"2028-05-01","to":"2028-05-01","description":"Sviatok práce"},{"from":"2028-07-05","to":"2028-07-05","description":"Sviatok svätého Cyrila a Metoda"},{"from":"2028-08-29","to":"2028-08-29","description":"Výročie Slovenského národného povstania"},{"from":"2028-11-01","to":"2028-11-01","description":"Sviatok všetkých svätých"},{"from":"2028-12-24","to":"2028-12-24","description":"Štedrý deň"},{"from":"2028-12-25","to":"2028-12-25","description":"Prvý sviatok vianočný"},{"from":"2028-12-26","to":"2028-12-26","description":"Druhý sviatok vianočný"}]}