{
  "category": "feiertage",
  "slug": "dk",
  "meta": {
    "title": "Danmark",
    "description": "Gesetzliche Feiertage für Danmark. Nächster Feiertag: Juledag am 25.12.2026.",
    "tags": [],
    "featured": false
  },
  "data": {
    "subject": {
      "slug": "dk",
      "category": "feiertage"
    },
    "source": [
      {
        "url": "https://www.npmjs.com/package/date-holidays",
        "license": "own_derivation",
        "license_note": "Eigene Ableitung aus den gesetzlichen Feiertagen der Bundesländer (Bibliothek date-holidays, basierend auf den jeweiligen Feiertagsgesetzen).",
        "retrieved_at": "2026-07-11",
        "extraction": "parser"
      }
    ],
    "windows": [
      {
        "type": "holiday",
        "year": 2026,
        "from": "2026-01-01",
        "to": "2026-01-01",
        "precision": "exact",
        "ics": true,
        "name": "Nytår"
      },
      {
        "type": "holiday",
        "year": 2026,
        "from": "2026-04-02",
        "to": "2026-04-02",
        "precision": "exact",
        "ics": true,
        "name": "Skærtorsdag"
      },
      {
        "type": "holiday",
        "year": 2026,
        "from": "2026-04-03",
        "to": "2026-04-03",
        "precision": "exact",
        "ics": true,
        "name": "Langfredag"
      },
      {
        "type": "holiday",
        "year": 2026,
        "from": "2026-04-05",
        "to": "2026-04-05",
        "precision": "exact",
        "ics": true,
        "name": "Påskesøndag"
      },
      {
        "type": "holiday",
        "year": 2026,
        "from": "2026-04-06",
        "to": "2026-04-06",
        "precision": "exact",
        "ics": true,
        "name": "Anden påskedag"
      },
      {
        "type": "holiday",
        "year": 2026,
        "from": "2026-05-14",
        "to": "2026-05-14",
        "precision": "exact",
        "ics": true,
        "name": "Kristi Himmelfartsdag"
      },
      {
        "type": "holiday",
        "year": 2026,
        "from": "2026-05-24",
        "to": "2026-05-24",
        "precision": "exact",
        "ics": true,
        "name": "Pinsedag"
      },
      {
        "type": "holiday",
        "year": 2026,
        "from": "2026-05-25",
        "to": "2026-05-25",
        "precision": "exact",
        "ics": true,
        "name": "Anden Pinsedag"
      },
      {
        "type": "holiday",
        "year": 2026,
        "from": "2026-12-25",
        "to": "2026-12-25",
        "precision": "exact",
        "ics": true,
        "name": "Juledag"
      },
      {
        "type": "holiday",
        "year": 2026,
        "from": "2026-12-26",
        "to": "2026-12-26",
        "precision": "exact",
        "ics": true,
        "name": "Anden Juledag"
      },
      {
        "type": "holiday",
        "year": 2027,
        "from": "2027-01-01",
        "to": "2027-01-01",
        "precision": "exact",
        "ics": true,
        "name": "Nytår"
      },
      {
        "type": "holiday",
        "year": 2027,
        "from": "2027-03-25",
        "to": "2027-03-25",
        "precision": "exact",
        "ics": true,
        "name": "Skærtorsdag"
      },
      {
        "type": "holiday",
        "year": 2027,
        "from": "2027-03-26",
        "to": "2027-03-26",
        "precision": "exact",
        "ics": true,
        "name": "Langfredag"
      },
      {
        "type": "holiday",
        "year": 2027,
        "from": "2027-03-28",
        "to": "2027-03-28",
        "precision": "exact",
        "ics": true,
        "name": "Påskesøndag"
      },
      {
        "type": "holiday",
        "year": 2027,
        "from": "2027-03-29",
        "to": "2027-03-29",
        "precision": "exact",
        "ics": true,
        "name": "Anden påskedag"
      },
      {
        "type": "holiday",
        "year": 2027,
        "from": "2027-05-06",
        "to": "2027-05-06",
        "precision": "exact",
        "ics": true,
        "name": "Kristi Himmelfartsdag"
      },
      {
        "type": "holiday",
        "year": 2027,
        "from": "2027-05-16",
        "to": "2027-05-16",
        "precision": "exact",
        "ics": true,
        "name": "Pinsedag"
      },
      {
        "type": "holiday",
        "year": 2027,
        "from": "2027-05-17",
        "to": "2027-05-17",
        "precision": "exact",
        "ics": true,
        "name": "Anden Pinsedag"
      },
      {
        "type": "holiday",
        "year": 2027,
        "from": "2027-12-25",
        "to": "2027-12-25",
        "precision": "exact",
        "ics": true,
        "name": "Juledag"
      },
      {
        "type": "holiday",
        "year": 2027,
        "from": "2027-12-26",
        "to": "2027-12-26",
        "precision": "exact",
        "ics": true,
        "name": "Anden Juledag"
      },
      {
        "type": "holiday",
        "year": 2028,
        "from": "2028-01-01",
        "to": "2028-01-01",
        "precision": "exact",
        "ics": true,
        "name": "Nytår"
      },
      {
        "type": "holiday",
        "year": 2028,
        "from": "2028-04-13",
        "to": "2028-04-13",
        "precision": "exact",
        "ics": true,
        "name": "Skærtorsdag"
      },
      {
        "type": "holiday",
        "year": 2028,
        "from": "2028-04-14",
        "to": "2028-04-14",
        "precision": "exact",
        "ics": true,
        "name": "Langfredag"
      },
      {
        "type": "holiday",
        "year": 2028,
        "from": "2028-04-16",
        "to": "2028-04-16",
        "precision": "exact",
        "ics": true,
        "name": "Påskesøndag"
      },
      {
        "type": "holiday",
        "year": 2028,
        "from": "2028-04-17",
        "to": "2028-04-17",
        "precision": "exact",
        "ics": true,
        "name": "Anden påskedag"
      },
      {
        "type": "holiday",
        "year": 2028,
        "from": "2028-05-25",
        "to": "2028-05-25",
        "precision": "exact",
        "ics": true,
        "name": "Kristi Himmelfartsdag"
      },
      {
        "type": "holiday",
        "year": 2028,
        "from": "2028-06-04",
        "to": "2028-06-04",
        "precision": "exact",
        "ics": true,
        "name": "Pinsedag"
      },
      {
        "type": "holiday",
        "year": 2028,
        "from": "2028-06-05",
        "to": "2028-06-05",
        "precision": "exact",
        "ics": true,
        "name": "Anden Pinsedag"
      },
      {
        "type": "holiday",
        "year": 2028,
        "from": "2028-12-25",
        "to": "2028-12-25",
        "precision": "exact",
        "ics": true,
        "name": "Juledag"
      },
      {
        "type": "holiday",
        "year": 2028,
        "from": "2028-12-26",
        "to": "2028-12-26",
        "precision": "exact",
        "ics": true,
        "name": "Anden Juledag"
      }
    ],
    "raw_data": {}
  },
  "events": [
    {
      "date": "2026-01-01",
      "label": "Nytår"
    },
    {
      "date": "2026-04-02",
      "label": "Skærtorsdag"
    },
    {
      "date": "2026-04-03",
      "label": "Langfredag"
    },
    {
      "date": "2026-04-05",
      "label": "Påskesøndag"
    },
    {
      "date": "2026-04-06",
      "label": "Anden påskedag"
    },
    {
      "date": "2026-05-14",
      "label": "Kristi Himmelfartsdag"
    },
    {
      "date": "2026-05-24",
      "label": "Pinsedag"
    },
    {
      "date": "2026-05-25",
      "label": "Anden Pinsedag"
    },
    {
      "date": "2026-12-25",
      "label": "Juledag"
    },
    {
      "date": "2026-12-26",
      "label": "Anden Juledag"
    },
    {
      "date": "2027-01-01",
      "label": "Nytår"
    },
    {
      "date": "2027-03-25",
      "label": "Skærtorsdag"
    },
    {
      "date": "2027-03-26",
      "label": "Langfredag"
    },
    {
      "date": "2027-03-28",
      "label": "Påskesøndag"
    },
    {
      "date": "2027-03-29",
      "label": "Anden påskedag"
    },
    {
      "date": "2027-05-06",
      "label": "Kristi Himmelfartsdag"
    },
    {
      "date": "2027-05-16",
      "label": "Pinsedag"
    },
    {
      "date": "2027-05-17",
      "label": "Anden Pinsedag"
    },
    {
      "date": "2027-12-25",
      "label": "Juledag"
    },
    {
      "date": "2027-12-26",
      "label": "Anden Juledag"
    },
    {
      "date": "2028-01-01",
      "label": "Nytår"
    },
    {
      "date": "2028-04-13",
      "label": "Skærtorsdag"
    },
    {
      "date": "2028-04-14",
      "label": "Langfredag"
    },
    {
      "date": "2028-04-16",
      "label": "Påskesøndag"
    },
    {
      "date": "2028-04-17",
      "label": "Anden påskedag"
    },
    {
      "date": "2028-05-25",
      "label": "Kristi Himmelfartsdag"
    },
    {
      "date": "2028-06-04",
      "label": "Pinsedag"
    },
    {
      "date": "2028-06-05",
      "label": "Anden Pinsedag"
    },
    {
      "date": "2028-12-25",
      "label": "Juledag"
    },
    {
      "date": "2028-12-26",
      "label": "Anden Juledag"
    }
  ]
}